MANIFEST.in
RELEASE-VERSION
get_git_version.py
setup.py
joyce.egg-info/PKG-INFO
joyce.egg-info/SOURCES.txt
joyce.egg-info/dependency_links.txt
joyce.egg-info/requires.txt
joyce.egg-info/top_level.txt
src/__init__.py
src/base.py
src/comet.py
src/light.py