Metadata-Version: 1.0
Name: joyce
Version: 0.1.9
Summary: JSON channels
Home-page: http://github.com/bwesterb/py-joyce/
Author: Bas Westerbaan
Author-email: bas@westerbaan.name
License: UNKNOWN
Platform: UNKNOWN
